backtick/__init__.py
backtick/backtick.py
backtick/cli.py
backtick-1.2.0.dist-info/LICENSE
backtick-1.2.0.dist-info/METADATA
backtick-1.2.0.dist-info/WHEEL
backtick-1.2.0.dist-info/entry_points.txt
backtick-1.2.0.dist-info/RECORD
