Metadata-Version: 2.3
Name: backtick
Version: 1.2.0
Summary: Backtick is a programming language with a short syntax.
License: MIT
Author: splot.dev
Requires-Python: >=3.10
Classifier: License :: OSI Approved :: MIT License
Classifier: Programming Language :: Python :: 3
Classifier: Programming Language :: Python :: 3.10
Classifier: Programming Language :: Python :: 3.11
Classifier: Programming Language :: Python :: 3.12
Classifier: Programming Language :: Python :: 3.13
Requires-Dist: filelock (>=3.20.0,<4.0.0)
Requires-Dist: platformdirs (>=3.10,<4.0.0)
Requires-Dist: requests (>=2.32.5,<3.0.0)
